docs/mkdocs/scripts/example_images.py
docs/mkdocs/scripts/release_note.py
test/test_algorithm.py
test/test_api.py
test/test_mlops.py
test/test_monitoring.py
test/test_plot.py
test/test_quant.py
test/test_util.py
test/test_vision.py
test/data/triton-inference-server/dynamic_batching/1/model.py
test/data/triton-inference-server/without_batching/1/model.py
zerohertzLib/__init__.py
zerohertzLib/algorithm/__init__.py
zerohertzLib/algorithm/bisect.py
zerohertzLib/algorithm/collections.py
zerohertzLib/algorithm/fft.py
zerohertzLib/algorithm/graph.py
zerohertzLib/algorithm/prime.py
zerohertzLib/algorithm/sort.py
zerohertzLib/api/__init__.py
zerohertzLib/api/base.py
zerohertzLib/api/discord.py
zerohertzLib/api/github.py
zerohertzLib/api/koreainvestment.py
zerohertzLib/api/slack.py
zerohertzLib/mlops/__init__.py
zerohertzLib/mlops/cli.py
zerohertzLib/mlops/client.py
zerohertzLib/mlops/server.py
zerohertzLib/monitoring/__init__.py
zerohertzLib/monitoring/cpu.py
zerohertzLib/monitoring/gpu.py
zerohertzLib/monitoring/storage.py
zerohertzLib/plot/__init__.py
zerohertzLib/plot/bar_chart.py
zerohertzLib/plot/config.py
zerohertzLib/plot/pie.py
zerohertzLib/plot/plot.py
zerohertzLib/plot/scatter.py
zerohertzLib/plot/table.py
zerohertzLib/plot/util.py
zerohertzLib/plot/fonts/NotoSerifKR-Medium.otf
zerohertzLib/plot/fonts/times.ttf
zerohertzLib/quant/__init__.py
zerohertzLib/quant/backtest.py
zerohertzLib/quant/koreainvestment.py
zerohertzLib/quant/methods.py
zerohertzLib/quant/quant.py
zerohertzLib/quant/util.py
zerohertzLib/util/__init__.py
zerohertzLib/util/csv.py
zerohertzLib/util/data.py
zerohertzLib/util/json.py
zerohertzLib/vision/__init__.py
zerohertzLib/vision/cli.py
zerohertzLib/vision/compare.py
zerohertzLib/vision/convert.py
zerohertzLib/vision/data.py
zerohertzLib/vision/eval.py
zerohertzLib/vision/gif.py
zerohertzLib/vision/loader.py
zerohertzLib/vision/transform.py
zerohertzLib/vision/util.py
zerohertzLib/vision/visual.py
zerohertzlib-1.2.7.dist-info/licenses/LICENSE
zerohertzlib-1.2.7.dist-info/METADATA
zerohertzlib-1.2.7.dist-info/WHEEL
zerohertzlib-1.2.7.dist-info/entry_points.txt
zerohertzlib-1.2.7.dist-info/top_level.txt
zerohertzlib-1.2.7.dist-info/RECORD
