Metadata-Version: 2.4
Name: zerohertzLib
Version: 1.2.7
Summary: Zerohertz's Library
Author-email: zerohertz <ohg3417@gmail.com>
Maintainer-email: zerohertz <ohg3417@gmail.com>
License-Expression: MIT
Project-URL: homepage, https://zerohertzlib.readthedocs.io/
Project-URL: documentation, https://zerohertzlib.readthedocs.io/
Project-URL: repository, https://github.com/Zerohertz/zerohertzLib
Project-URL: changelog, https://zerohertzlib.readthedocs.io/
Keywords: Scientific/Engineering,Mathematics,Artificial Intelligence,Software Development,Libraries
Classifier: Development Status :: 5 - Production/Stable
Classifier: Intended Audience :: Developers
Classifier: Intended Audience :: Education
Classifier: Intended Audience :: Science/Research
Classifier: Topic :: Scientific/Engineering
Classifier: Topic :: Scientific/Engineering :: Mathematics
Classifier: Topic :: Scientific/Engineering :: Artificial Intelligence
Classifier: Topic :: Software Development
Classifier: Topic :: Software Development :: Libraries
Classifier: Topic :: Software Development :: Libraries :: Python Modules
Classifier: Programming Language :: Python
Classifier: Programming Language :: Python :: 3
Classifier: Programming Language :: Python :: 3.10
Classifier: Programming Language :: Python :: 3.11
Classifier: Programming Language :: Python :: 3.12
Classifier: Programming Language :: Python :: 3.13
Requires-Python: >=3.10
License-File: LICENSE
Requires-Dist: psutil
Requires-Dist: matplotlib>=3.5.2
Requires-Dist: seaborn>=0.12
Requires-Dist: pandas
Requires-Dist: mplfinance
Requires-Dist: tqdm
Requires-Dist: orjson
Requires-Dist: numpy
Requires-Dist: opencv-python
Requires-Dist: Pillow>=10.0.0
Requires-Dist: shapely
Provides-Extra: api
Requires-Dist: requests; extra == "api"
Requires-Dist: slack_sdk; extra == "api"
Provides-Extra: mlops
Requires-Dist: requests; extra == "mlops"
Requires-Dist: slack_sdk; extra == "mlops"
Requires-Dist: protobuf; extra == "mlops"
Requires-Dist: tritonclient[grpc]>=2.44.0; extra == "mlops"
Requires-Dist: prettytable; extra == "mlops"
Requires-Dist: loguru; extra == "mlops"
Provides-Extra: quant
Requires-Dist: requests; extra == "quant"
Requires-Dist: slack_sdk; extra == "quant"
Requires-Dist: finance-datareader>=0.9.94; extra == "quant"
Requires-Dist: prettytable; extra == "quant"
Provides-Extra: all
Requires-Dist: requests; extra == "all"
Requires-Dist: slack_sdk; extra == "all"
Requires-Dist: prettytable; extra == "all"
Requires-Dist: protobuf; extra == "all"
Requires-Dist: tritonclient[grpc]>=2.44.0; extra == "all"
Requires-Dist: loguru; extra == "all"
Requires-Dist: finance-datareader>=0.9.94; extra == "all"
Dynamic: license-file
